__init__.py
metacast/__init__.py
metacast/infection_seeding.py
metacast/metacaster.py
metacast/event_handling/__init__.py
metacast/event_handling/event_queue.py
metacast/event_handling/events.py
metacast/sensitivity_analyses/__init__.py
metacast/sensitivity_analyses/asses_lh_sample_size.py
metacast/sensitivity_analyses/lhs_and_prcc.py
metacast-0.2.0.dist-info/LICENSE
metacast-0.2.0.dist-info/METADATA
metacast-0.2.0.dist-info/WHEEL
metacast-0.2.0.dist-info/top_level.txt
metacast-0.2.0.dist-info/RECORD
