Metadata-Version: 2.1
Name: metacast
Version: 0.2.0
Summary: A package for broadcasting epidemiological and ecological models over meta-populations.
Author-email: Martin Grunnill <m.d.grunnill@gmail.com>
Maintainer-email: Martin Grunnill <m.d.grunnill@gmail.com>
License: Apache License
Project-URL: Homepage, https://github.com/m-d-grunnill/MetaCast
Project-URL: Repository, https://github.com/m-d-grunnill/MetaCast
Project-URL: Issues, https://github.com/m-d-grunnill/MetaCast/issues
Project-URL: Documentaion, https://metacast.readthedocs.io/en/latest/index.html
Keywords: Epimediology,Ecology,Virology,Compartmental,Model,Metapopulations,Structured Populations,Discrete Event,Sensitivity Analyses,Latin Hypercube Sampling,Scenario Analysis
Classifier: Development Status :: 4 - Beta
Classifier: Programming Language :: Python :: 3.10
Classifier: License :: OSI Approved :: Apache Software License
Classifier: Operating System :: OS Independent
Classifier: Natural Language :: English
Classifier: Topic :: Scientific/Engineering
Classifier: Intended Audience :: Science/Research
Requires-Python: >=3.10
License-File: LICENSE
Requires-Dist: numpy >=1.26.3
Requires-Dist: pandas >=2.1.4
Requires-Dist: scipy >=1.11.4
Requires-Dist: pingouin >=0.5.4
Requires-Dist: tqdm >=4.66.1
Requires-Dist: dask >=2024.2.1
Requires-Dist: distributed >=2024.2.1
Requires-Dist: bokeh >=3.3.4
Requires-Dist: seaborn >=0.13.2
Requires-Dist: jupyter >=1.0.0
